{"build_type": "release", "env_name": "ATtiny1616", "libsource_dirs": ["/home/bart/Repos/StackCabinet/cab/lib", "/home/bart/Repos/StackCabinet/cab/.pio/libdeps/ATtiny1616", "/home/bart/.platformio/lib"], "defines": ["F_CPU=16000000L", "PLATFORMIO=60105", "ARDUINO_attinyxy6", "MILLIS_USE_TIMERD0", "UARTBAUD5V"], "includes": {"build": ["/home/bart/Repos/StackCabinet/cab/include", "/home/bart/Repos/StackCabinet/cab/src", "/home/bart/Repos/StackCabinet/cab/include", "/home/bart/Repos/StackCabinet/cab/src", "/home/bart/Repos/StackCabinet/cab/lib/SCCP"], "compatlib": ["/home/bart/Repos/StackCabinet/cab/lib/SCCP"], "toolchain": ["/home/bart/.platformio/packages/toolchain-atmelavr@1.70300.191015/lib/gcc/avr/7.3.0/include-fixed", "/home/bart/.platformio/packages/toolchain-atmelavr@1.70300.191015/lib/gcc/avr/7.3.0/include", "/home/bart/.platformio/packages/toolchain-atmelavr@1.70300.191015/avr/include"]}, "cc_flags": "-std=gnu11 -fno-fat-lto-objects -mmcu=attiny1616 -Os -w -ffunction-sections -fdata-sections -flto", "cxx_flags": "-std=gnu++11 -fno-exceptions -fno-threadsafe-statics -fpermissive -Wno-error=narrowing -mmcu=attiny1616 -Os -w -ffunction-sections -fdata-sections -flto", "cc_path": "/home/bart/.platformio/packages/toolchain-atmelavr@1.70300.191015/bin/avr-gcc", "cxx_path": "/home/bart/.platformio/packages/toolchain-atmelavr@1.70300.191015/bin/avr-g++", "gdb_path": "/home/bart/.platformio/packages/toolchain-atmelavr@1.70300.191015/bin/avr-gdb", "prog_path": "/home/bart/Repos/StackCabinet/cab/.pio/build/ATtiny1616/firmware.elf", "svd_path": null, "compiler_type": "gcc", "targets": [{"name": "size", "title": "Program Size", "description": "Calculate program size", "group": "Platform"}, {"name": "fuses", "title": "Set Fuses", "description": null, "group": "Platform"}, {"name": "bootloader", "title": "Burn Bootloader", "description": null, "group": "Platform"}, {"name": "upload", "title": "Upload", "description": null, "group": "Platform"}], "extra": {"flash_images": []}}